<annotation>
	<folder>train_data</folder>
	<filename>drishti_Aadhar_page_page-0001.jpg</filename>
	<path>/Users/apple/Downloads/doc_verification/data/train_data/drishti_Aadhar_page_page-0001.jpg</path>
	<source>
		<database>Unknown</database>
	</source>
	<size>
		<width>1275</width>
		<height>1650</height>
		<depth>3</depth>
	</size>
	<segmented>0</segmented>
	<object>
		<name>photo</name>
		<pose>Unspecified</pose>
		<truncated>0</truncated>
		<difficult>0</difficult>
		<bndbox>
			<xmin>372</xmin>
			<ymin>370</ymin>
			<xmax>536</xmax>
			<ymax>577</ymax>
		</bndbox>
	</object>
	<object>
		<name>name</name>
		<pose>Unspecified</pose>
		<truncated>0</truncated>
		<difficult>0</difficult>
		<bndbox>
			<xmin>541</xmin>
			<ymin>388</ymin>
			<xmax>669</xmax>
			<ymax>454</ymax>
		</bndbox>
	</object>
	<object>
		<name>dob</name>
		<pose>Unspecified</pose>
		<truncated>0</truncated>
		<difficult>0</difficult>
		<bndbox>
			<xmin>691</xmin>
			<ymin>455</ymin>
			<xmax>811</xmax>
			<ymax>489</ymax>
		</bndbox>
	</object>
	<object>
		<name>aadhaar_no</name>
		<pose>Unspecified</pose>
		<truncated>0</truncated>
		<difficult>0</difficult>
		<bndbox>
			<xmin>535</xmin>
			<ymin>562</ymin>
			<xmax>757</xmax>
			<ymax>603</ymax>
		</bndbox>
	</object>
</annotation>
